amulet/resource_pack/__init__.py
amulet/resource_pack/__init__.pyi
amulet/resource_pack/_amulet_resource_pack.cpython-311-darwin.so
amulet/resource_pack/_amulet_resource_pack.pyi
amulet/resource_pack/_load.py
amulet/resource_pack/_version.py
amulet/resource_pack/amulet_resource_packConfig.cmake
amulet/resource_pack/dll.hpp
amulet/resource_pack/libamulet_resource_pack.dylib
amulet/resource_pack/py.typed
amulet/resource_pack/unknown_resource_pack.py
amulet/resource_pack/__pyinstaller/__init__.py
amulet/resource_pack/__pyinstaller/hook-amulet.resource_pack.py
amulet/resource_pack/abc/__init__.py
amulet/resource_pack/abc/__init__.pyi
amulet/resource_pack/abc/resource_pack.py
amulet/resource_pack/abc/resource_pack_manager.py
amulet/resource_pack/image/__init__.pyi
amulet/resource_pack/image/image.hpp
amulet/resource_pack/image/missing_pack.png
amulet/resource_pack/java/__init__.py
amulet/resource_pack/java/__init__.pyi
amulet/resource_pack/java/download_resources.py
amulet/resource_pack/java/resource_pack.py
amulet/resource_pack/java/resource_pack_manager.py
amulet/resource_pack/java/java_vanilla_fix/pack.mcmeta
amulet/resource_pack/java/java_vanilla_fix/pack.png
amulet/resource_pack/java/java_vanilla_fix/assets/minecraft/blockstates/acacia_sign.json
amulet/resource_pack/java/java_vanilla_fix/assets/minecraft/blockstates/acacia_wall_sign.json
amulet/resource_pack/java/java_vanilla_fix/assets/minecraft/blockstates/birch_sign.json
amulet/resource_pack/java/java_vanilla_fix/assets/minecraft/blockstates/birch_wall_sign.json
amulet/resource_pack/java/java_vanilla_fix/assets/minecraft/blockstates/black_banner.json
amulet/resource_pack/java/java_vanilla_fix/assets/minecraft/blockstates/black_bed.json
amulet/resource_pack/java/java_vanilla_fix/assets/minecraft/blockstates/black_wall_banner.json
amulet/resource_pack/java/java_vanilla_fix/assets/minecraft/blockstates/blue_banner.json
amulet/resource_pack/java/java_vanilla_fix/assets/minecraft/blockstates/blue_bed.json
amulet_resource_pack-1.0.2a5.dist-info/METADATA
amulet_resource_pack-1.0.2a5.dist-info/WHEEL
amulet_resource_pack-1.0.2a5.dist-info/entry_points.txt
amulet_resource_pack-1.0.2a5.dist-info/top_level.txt
amulet_resource_pack-1.0.2a5.dist-info/RECORD
